engram_mcp/__init__.py
engram_mcp/__main__.py
engram_mcp/server.py
engram_mcp-0.1.0.dist-info/METADATA
engram_mcp-0.1.0.dist-info/WHEEL
engram_mcp-0.1.0.dist-info/entry_points.txt
engram_mcp-0.1.0.dist-info/RECORD
