Metadata-Version: 2.4
Name: engram-mcp
Version: 0.1.0
Summary: The permanent and semantic memory layer for AI agents
Project-URL: Repository, https://github.com/shubhamomar/engram-mcp
Author-email: Shubham Omar <shubhamomar53@gmail.com>
License: MIT
Requires-Python: >=3.10
Requires-Dist: fastmcp
Requires-Dist: mcp
Requires-Dist: notion-client
Requires-Dist: python-dotenv
